<?xml version="1.0" ?>
<poem>
  <phead>
    <ptitle>Sonnet 136</ptitle>
    <author>
      <first-name>William</first-name>
      <last-name>Shakespeare</last-name>
    </author>
  </phead>
  <pbody>
    <stanza>
      <line>If thy soul check thee that I come so near</line>
      <line>Swear to thy blind soul that I was thy Will</line>
      <line>And will thy soul knows is admitted there</line>
      <line>Thus far for love my love suit sweet fulfil</line>
      <line>Will will fulfil the treasure of thy love</line>
      <line>Ay fill it full with wills and my will one</line>
      <line>In things of great receipt with case we prove</line>
      <line>Among a number one is reckoned none</line>
      <line>Then in the number let me pass untold</line>
      <line>Though in thy store account I one must be</line>
      <line>For nothing hold me so it please thee hold</line>
      <line>That nothing me a something sweet to thee</line>
      <line>Make but my name thy love and love that still</line>
      <line>And then thou lov me for my name is Will</line>
    </stanza>
  </pbody>
</poem>
