<poem>
  <phead>
    <ptitle>Sonnet 144</ptitle>
    <author>
      <first-name>William</first-name>
      <last-name>Shakespeare</last-name>
    </author>
  </phead>
  <pbody>
    <stanza>
      <line>Two loves I have of comfort and despair<phoneme category="a">despair</phoneme></line>
      <line>Which like two spirits do suggest me still<phoneme category="b">still</phoneme></line>
      <line>The better angel is a man right fair<phoneme category="a">fair</phoneme></line>
      <line>The worser spirit a woman coloured ill<phoneme category="b">ill</phoneme></line>
      <line>To win me soon to hell my female evil<phoneme category="c">evil</phoneme></line>
      <line>Tempteth my better angel from my side<phoneme category="d">side</phoneme></line>
      <line>And would corrupt my saint to be a devil<phoneme category="c">devil</phoneme></line>
      <line>Wooing his purity with her foul pride<phoneme category="d">pride</phoneme></line>
      <line>And whether that my angel be turned fiend<phoneme category="e">fiend</phoneme></line>
      <line>Suspect I may yet not directly tell<phoneme category="f">tell</phoneme></line>
      <line>But being both from me both to each friend<phoneme category="e">friend</phoneme></line>
      <line>I guess one angel in another hell<phoneme category="f">hell</phoneme></line>
      <line>Yet this shall I neer know but live in doubt<phoneme category="g">doubt</phoneme></line>
      <line>Till my bad angel fire my good one out<phoneme category="g">out</phoneme></line>
    </stanza>
  </pbody>
</poem>