<poem>
  <phead>
    <ptitle>Sonnet 115</ptitle>
    <author>
      <first-name>William</first-name>
      <last-name>Shakespeare</last-name>
    </author>
  </phead>
  <pbody>
    <stanza>
      <line><text>Those lines that I before have writ do lie</text><meter>s s* s s* s s* s s* s s*</meter></line>
      <line><text>Even those that said I could not love you dearer</text><meter>s s* s s* s s* s s* s s*</meter></line>
      <line><text>Yet then my judgment knew no reason why</text><meter>s s* s s* s s* s s* s s*</meter></line>
      <line><text>My most full flame should afterwards burn clearer</text><meter>s s* s s* s s* s s* s s*</meter></line>
      <line><text>But reckoning time whose millioned accidents</text><meter>s s* s s* s s* s s* s s*</meter></line>
      <line><text>Creep in twixt vows and change decrees of kings</text><meter>s s* s s* s s* s s* s s*</meter></line>
      <line><text>Tan sacred beauty blunt the sharp intents</text><meter>s s* s s* s s* s s* s s*</meter></line>
      <line><text>Divert strong minds to the course of altring things</text><meter>s s* s s* s s* s s* s s*</meter></line>
      <line><text>Alas why fearing of time tyranny</text><meter>s s* s s* s s* s s* s s*</meter></line>
      <line><text>Might I not then say Now I love you best</text><meter>s s* s s* s s* s s* s s*</meter></line>
      <line><text>When I was certain oer incertainty</text><meter>s s* s s* s s* s s* s s*</meter></line>
      <line><text>Crowning the present doubting of the rest</text><meter>s s* s s* s s* s s* s s*</meter></line>
      <line><text>Love is a babe then might I not say so</text><meter>s s* s s* s s* s s* s s*</meter></line>
      <line><text>To give full growth to that which still doth grow</text><meter>s s* s s* s s* s s* s s*</meter></line>
    </stanza>
  </pbody>
</poem>